dota2hero
